{
    "pools": [
        {
            "entries": [
                {
                    "functions": [
                        {
                            "count": {
                                "max": 5,
                                "min": 5
                            },
                            "function": "set_count"
                        }
                    ],
                    "name": "minecraft:brown_mushroom",
                    "type": "item"
                }
            ],
            "rolls": 1
        }
    ]
}