{
    "format_version": "1.12",
    "minecraft:recipe_shapeless": {
        "description": {
            "identifier": "arris:honey_cookie"
        },
        "ingredients": [
            {
                "count": 1,
                "data": 0,
                "item": "minecraft:honey_bottle"
            },
            {
                "count": 2,
                "data": 0,
                "item": "minecraft:wheat"
            }
        ],
        "result": {
            "count": 8,
            "data": 0,
            "item": "arris:honey_cookie"
        },
        "tags": [
            "crafting_table"
        ]
    }
}